{
  "delta_name": "p0_gap_closure_delta",
  "p0_gap_closure_delta_complete": false,
  "p0_gap_closure_delta_digest": "7bedc5c973ee638f4c6f988bdd9a9e9daec927053f0af86cd2c18cc09a2b4113",
  "p0_gap_closure_delta_locked": false,
  "p0_gap_closure_delta_status": "P0_1_INSTALL_CONTRACT_GAP_NOT_CLOSED",
  "p0_gap_closure_items": [
    {
      "closed": false,
      "closed_by": null,
      "domain": "install_contract",
      "gap_id": "P0_INSTALL_CONTRACT_ALIGNMENT"
    },
    {
      "closed": false,
      "closed_by": null,
      "domain": "repo_hygiene",
      "gap_id": "P0_REPO_HYGIENE_EVIDENCE_RETENTION"
    },
    {
      "closed": false,
      "closed_by": null,
      "domain": "strict_config",
      "gap_id": "P0_STRICT_CONFIG_UNKNOWN_KEY_FAIL_CLOSED"
    },
    {
      "closed": false,
      "closed_by": null,
      "domain": "api_security",
      "gap_id": "P0_API_AUTH_DESTRUCTIVE_ENDPOINT_GUARD"
    },
    {
      "closed": false,
      "closed_by": null,
      "domain": "operator_controls",
      "gap_id": "P0_TYPED_CONFIRMATION_DESTRUCTIVE_ACTIONS"
    },
    {
      "closed": false,
      "closed_by": null,
      "domain": "persistence",
      "gap_id": "P0_SQLITE_AUDIT_BASELINE"
    },
    {
      "closed": false,
      "closed_by": null,
      "domain": "runtime_safety",
      "gap_id": "P0_RUNTIME_PROCESS_LOCK"
    },
    {
      "closed": false,
      "closed_by": null,
      "domain": "execution_cost_model",
      "gap_id": "P0_FEE_SLIPPAGE_BASELINE"
    },
    {
      "closed": false,
      "closed_by": null,
      "domain": "evidence_governance",
      "gap_id": "P0_REPORT_COMMIT_POLICY"
    },
    {
      "closed": false,
      "closed_by": null,
      "domain": "promotion_governance",
      "gap_id": "P0_PROMOTION_GATE_ISOLATION"
    }
  ],
  "p0_hardening_auto_close_allowed": false,
  "p0_hardening_closed_gap_count_after_37b": 0,
  "p0_hardening_complete": false,
  "p0_hardening_gap_count_after_37b": 10,
  "p0_hardening_open_gap_count_after_37b": 10,
  "p0_hardening_performed": false,
  "p0_install_contract_alignment_closed": false,
  "p0_install_contract_alignment_closed_by": null
}
